django_query_profiler/__init__.py
django_query_profiler/settings.py
django_query_profiler/chrome_plugin_helpers/__init__.py
django_query_profiler/chrome_plugin_helpers/redis_utils.py
django_query_profiler/chrome_plugin_helpers/views.py
django_query_profiler/client/__init__.py
django_query_profiler/client/context_manager.py
django_query_profiler/client/middleware.py
django_query_profiler/client/urls.py
django_query_profiler/django/__init__.py
django_query_profiler/django/contrib/__init__.py
django_query_profiler/django/contrib/gis/__init__.py
django_query_profiler/django/contrib/gis/db/__init__.py
django_query_profiler/django/contrib/gis/db/backends/__init__.py
django_query_profiler/django/contrib/gis/db/backends/postgis/__init__.py
django_query_profiler/django/contrib/gis/db/backends/postgis/base.py
django_query_profiler/django/db/__init__.py
django_query_profiler/django/db/backends/__init__.py
django_query_profiler/django/db/backends/cursor_wrapper_instrumentation.py
django_query_profiler/django/db/backends/database_wrapper_mixin.py
django_query_profiler/django/db/backends/mysql/__init__.py
django_query_profiler/django/db/backends/mysql/base.py
django_query_profiler/django/db/backends/oracle/__init__.py
django_query_profiler/django/db/backends/oracle/base.py
django_query_profiler/django/db/backends/postgresql/__init__.py
django_query_profiler/django/db/backends/postgresql/base.py
django_query_profiler/django/db/backends/sqlite3/__init__.py
django_query_profiler/django/db/backends/sqlite3/base.py
django_query_profiler/query_profiler_storage/__init__.py
django_query_profiler/query_profiler_storage/data_collector.py
django_query_profiler/query_profiler_storage/django_stack_trace_analyze.py
django_query_profiler/query_profiler_storage/stack_tracer.py
django_query_profiler/templates/django_query_profiler_level_query.html
django_query_profiler/templates/django_query_profiler_level_query_signature.html
django_query_profiler/templatetags/__init__.py
django_query_profiler-0.9.dist-info/LICENSE
django_query_profiler-0.9.dist-info/METADATA
django_query_profiler-0.9.dist-info/WHEEL
django_query_profiler-0.9.dist-info/top_level.txt
django_query_profiler-0.9.dist-info/RECORD
